credslayer/__init__.py
credslayer/credslayer.py
credslayer/core/__init__.py
credslayer/core/extract.py
credslayer/core/logger.py
credslayer/core/manager.py
credslayer/core/session.py
credslayer/core/utils.py
credslayer/parsers/__init__.py
credslayer/parsers/ftp.py
credslayer/parsers/http.py
credslayer/parsers/imap.py
credslayer/parsers/kerberos.py
credslayer/parsers/ldap.py
credslayer/parsers/mysql.py
credslayer/parsers/ntlmssp.py
credslayer/parsers/pgsql.py
credslayer/parsers/pop.py
credslayer/parsers/smtp.py
credslayer/parsers/snmp.py
credslayer/parsers/telnet.py
CredSLayer-0.1.3.dist-info/LICENSE
CredSLayer-0.1.3.dist-info/METADATA
CredSLayer-0.1.3.dist-info/WHEEL
CredSLayer-0.1.3.dist-info/entry_points.txt
CredSLayer-0.1.3.dist-info/top_level.txt
CredSLayer-0.1.3.dist-info/RECORD
