Metadata-Version: 2.1
Name: CredSLayer
Version: 0.1.3
Summary: Extract credentials and other useful info from network captures
Home-page: https://github.com/ShellCode33/CredSLayer
Author: ShellCode
Author-email: shellcode33@protonmail.ch
License: GPLv3
Keywords: credentials security networking extraction mining wireshark tshark dissector password
Platform: UNKNOWN
Classifier: Programming Language :: Python :: 3.5
Classifier: Programming Language :: Python :: 3.6
Classifier: Programming Language :: Python :: 3.7
Classifier: Programming Language :: Python :: 3.8
Classifier: License :: OSI Approved :: GNU General Public License v3 (GPLv3)
Classifier: Operating System :: POSIX :: Linux
Requires-Python: >=3.5
License-File: LICENSE
Requires-Dist: pyshark
